[
    { "phone": "6692141979", "name": "Meagan Vu" , "team": "Host", "captain": false},
    { "phone": "6504774562", "name": "Beatrice Hackman", "team": "SCU", "captain": false},
    { "phone": "8083210336", "name": "Nicholas Cheung", "team": "SCU", "captain": true},
    { "phone": "6508686668", "name": "Zaira Adrianwala" , "team": "UCSD", "captain": true},
    {"phone": "4153127743", "name": "Graham Yater" , "team": "Lick", "captain": false},
    {"phone": "5103311437", "name": "Jeannie Moreno" , "team": "Lick", "captain": true},
    {"phone": "4158236690", "name": "Jeffrey Jiang" , "team": "Lick", "captain": false},
    {"phone": "6084220301", "name": "Rachel Campbell" , "team": "Lick", "captain": false},
    {"phone": "4156085071", "name": "Ryan Chin" , "team": "Lick", "captain": false},
    {"phone": "5107088883", "name": "Kadie Qi" , "team": "UCSD", "captain": false},
    {"phone": "2068862090", "name": "Leon" , "team": "UCSD", "captain": false},
    {"phone": "7326406830", "name": "Sahil Sankur" , "team": "UCSD", "captain": false},
    {"phone": "07032003", "name": "TV Display"}
  ]